pidx/__init__.py
pidx/_modidx.py
pidx/attr.py
pidx/atyp.py
pidx/cons.py
pidx/enum.py
pidx/flat.py
pidx/idxs.py
pidx/mock.py
pidx/safe.py
pidx/smpl.py
pidx/util.py
pidx-0.0.15.dist-info/LICENSE
pidx-0.0.15.dist-info/METADATA
pidx-0.0.15.dist-info/WHEEL
pidx-0.0.15.dist-info/entry_points.txt
pidx-0.0.15.dist-info/top_level.txt
pidx-0.0.15.dist-info/RECORD
