Metadata-Version: 2.1
Name: pidx
Version: 0.0.15
Summary: power index pandas index
Home-page: https://github.com/dsm-72/pidx
Author: dsm-72
Author-email: sumner.magruder@yale.edu
License: Apache Software License 2.0
Keywords: pidx power pandas pd index
Classifier: Development Status :: 4 - Beta
Classifier: Intended Audience :: Developers
Classifier: Natural Language :: English
Classifier: Programming Language :: Python :: 3.11
Classifier: License :: OSI Approved :: Apache Software License
Requires-Python: >=3.11
License-File: LICENSE
Requires-Dist: quac
Requires-Dist: putl
Requires-Dist: asto
Requires-Dist: atup
Requires-Dist: chck
Requires-Dist: excs
Requires-Dist: astr
Requires-Dist: nchr
Requires-Dist: nlit
Provides-Extra: dev
Requires-Dist: numpy ; extra == 'dev'
Requires-Dist: pandas ; extra == 'dev'
Requires-Dist: torch ; extra == 'dev'
Requires-Dist: torchvision ; extra == 'dev'
Requires-Dist: pytorch-lightning ; extra == 'dev'
